Metadata-Version: 2.1
Name: tyy-upload
Version: 6.1.4
Summary: upload file
Home-page: UNKNOWN
Author: hxl
Maintainer: hxl
License: MIT License
Platform: UNKNOWN
Classifier: Programming Language :: Python :: 3
Classifier: License :: OSI Approved :: MIT License
Classifier: Operating System :: OS Independent
License-File: LICENSE
